maios3/__init__.py
maios3/base.py
maios3-0.0.2.dist-info/METADATA
maios3-0.0.2.dist-info/WHEEL
maios3-0.0.2.dist-info/top_level.txt
maios3-0.0.2.dist-info/RECORD
